langgraph_executor/__init__.py
langgraph_executor/executor.py
langgraph_executor/executor_base.py
langgraph_executor/info_logger.py
langgraph_executor/py.typed
langgraph_executor/remote_store.py
langgraph_executor/serde.py
langgraph_executor/server.py
langgraph_executor/stream_utils.py
langgraph_executor-0.0.1a16.dist-info/METADATA
langgraph_executor-0.0.1a16.dist-info/WHEEL
langgraph_executor-0.0.1a16.dist-info/RECORD
